data/__init__.py
data/data_cleaner.py
data/data_dictionary.py
data/sets_subsets.py
model/__init__.py
packages_mental_disorder_eeg_data-0.0.4.dist-info/licenses/LICENSE
packages_mental_disorder_eeg_data-0.0.4.dist-info/METADATA
packages_mental_disorder_eeg_data-0.0.4.dist-info/WHEEL
packages_mental_disorder_eeg_data-0.0.4.dist-info/top_level.txt
packages_mental_disorder_eeg_data-0.0.4.dist-info/RECORD
