Metadata-Version: 2.4
Name: packages-mental-disorder-eeg-data
Version: 0.0.4
Summary: Pacote para manipular conjuntos
Home-page: 
Author: Mateus Balda Mota
Author-email: mateusbalda89@gmail.com
Classifier: Programming Language :: Python :: 3
Classifier: License :: OSI Approved :: MIT License
Classifier: Operating System :: OS Independent
Requires-Python: >=3.8
License-File: LICENSE
Requires-Dist: pandas
Dynamic: author
Dynamic: author-email
Dynamic: classifier
Dynamic: description-content-type
Dynamic: license-file
Dynamic: requires-dist
Dynamic: requires-python
Dynamic: summary
